halohome/__init__.py
halohome-0.7.0.dist-info/LICENSE
halohome-0.7.0.dist-info/METADATA
halohome-0.7.0.dist-info/WHEEL
halohome-0.7.0.dist-info/top_level.txt
halohome-0.7.0.dist-info/RECORD
