Metadata-Version: 2.1
Name: halohome
Version: 0.7.0
Summary: A python library to control Eaton HALO Home Smart Lights
Home-page: https://github.com/nayaverdier/halohome
Author: Naya Verdier
License: MIT
Classifier: Programming Language :: Python
Classifier: Programming Language :: Python :: 3
Requires-Python: >=3.7
License-File: LICENSE
Requires-Dist: aiohttp ~=3.7
Requires-Dist: bleak ~=0.13
Requires-Dist: csrmesh ~=0.10
Provides-Extra: dev
Requires-Dist: black ==23.3.0 ; extra == 'dev'
Requires-Dist: flake8 ==5.0.4 ; extra == 'dev'
Requires-Dist: flake8-bugbear ==23.3.12 ; extra == 'dev'
Requires-Dist: isort ==5.11.5 ; extra == 'dev'
Requires-Dist: twine ==4.0.2 ; extra == 'dev'
Requires-Dist: wheel ==0.42.0 ; extra == 'dev'
